model_hooks/__init__.py
model_hooks/admin.py
model_hooks/apps.py
model_hooks/decorators.py
model_hooks/events.py
model_hooks/forms.py
model_hooks/models.py
model_hooks/receivers.py
model_hooks/signals.py
model_hooks/utils.py
model_hooks/version.py
model_hooks/management/__init__.py
model_hooks/management/commands/__init__.py
model_hooks/management/commands/log_prune.py
model_hooks/migrations/0001_initial.py
model_hooks/migrations/__init__.py
django_model_hooks-1.0.1.dist-info/METADATA
django_model_hooks-1.0.1.dist-info/WHEEL
django_model_hooks-1.0.1.dist-info/top_level.txt
django_model_hooks-1.0.1.dist-info/RECORD
