Metadata-Version: 2.1
Name: django-model-hooks
Version: 1.0.1
Summary: Model hooks for Django
Home-page: https://gitlab.com/luggagecare/django-model-hooks
Author: Bram Boogaard
Author-email: bram@luggo.nl
License: MIT License
Keywords: Django Model hooks
Classifier: Development Status :: 3 - Alpha
Requires-Dist: pytest
Requires-Dist: pytest-cov
Requires-Dist: pytest-django
Requires-Dist: django ~=4.2.7
